shpc/__init__.py
shpc/defaults.py
shpc/logger.py
shpc/settings.yml
shpc/version.py
shpc/client/__init__.py
shpc/client/add.py
shpc/client/check.py
shpc/client/config.py
shpc/client/docgen.py
shpc/client/get.py
shpc/client/help.py
shpc/client/inspect.py
shpc/client/install.py
shpc/client/listing.py
shpc/client/namespace.py
shpc/client/pull.py
shpc/client/remove.py
shpc/client/shell.py
shpc/client/show.py
shpc/client/sync.py
shpc/client/test.py
shpc/client/uninstall.py
shpc/client/update.py
shpc/client/view.py
shpc/main/__init__.py
shpc/main/client.py
shpc/main/schemas.py
shpc/main/settings.py
shpc/main/templates.py
shpc/main/container/__init__.py
shpc/main/container/base.py
shpc/main/container/config.py
shpc/main/container/docker.py
shpc/main/container/podman.py
shpc/main/container/singularity.py
shpc/main/container/templates/__init__.py
shpc/main/container/templates/container.yaml
shpc/main/container/update/__init__.py
shpc/main/container/update/diff.py
shpc/main/container/update/docker.py
shpc/main/container/update/versions.py
shpc/main/modules/__init__.py
shpc/main/modules/base.py
shpc/main/modules/lmod.py
shpc/main/modules/module.py
shpc/main/modules/tcl.py
shpc/main/modules/template.py
shpc/main/modules/versions.py
shpc/main/modules/views.py
shpc/main/modules/templates/__init__.py
shpc/main/modules/templates/default_version
shpc/main/modules/templates/docker.lua
shpc/main/modules/templates/docker.tcl
shpc/main/modules/templates/docs.md
shpc/main/modules/templates/singularity.lua
shpc/main/modules/templates/singularity.tcl
shpc/main/modules/templates/test.sh
shpc/main/modules/templates/view_module.lua
shpc/main/modules/templates/view_module.tcl
shpc/main/modules/templates/includes/default_version.lua
shpc/main/modules/templates/includes/load_view.lua
shpc/main/modules/templates/includes/load_view.tcl
shpc/main/registry/__init__.py
shpc/main/registry/filesystem.py
shpc/main/registry/provider.py
shpc/main/registry/remote.py
shpc/main/wrappers/__init__.py
singularity_hpc-0.1.32.dist-info/LICENSE
singularity_hpc-0.1.32.dist-info/METADATA
singularity_hpc-0.1.32.dist-info/WHEEL
singularity_hpc-0.1.32.dist-info/entry_points.txt
singularity_hpc-0.1.32.dist-info/top_level.txt
singularity_hpc-0.1.32.dist-info/RECORD
