Metadata-Version: 2.2
Name: singularity-hpc
Version: 0.1.32
Summary: Local registry intended for HPC using containers and system modules.
Home-page: https://github.com/singularityhub/singularity-hpc
Author: Vanessa Sochat
Author-email: vsoch@users.noreply.github.com
Maintainer: Vanessa Sochat
License: LICENSE
Keywords: singularity,containers,hpc,lmd
Classifier: Intended Audience :: Science/Research
Classifier: Intended Audience :: Developers
Classifier: License :: OSI Approved :: Mozilla Public License 2.0 (MPL 2.0)
Classifier: Programming Language :: C
Classifier: Programming Language :: Python
Classifier: Topic :: Software Development
Classifier: Topic :: Scientific/Engineering
Classifier: Operating System :: Unix
Classifier: Programming Language :: Python :: 3.7
License-File: LICENSE
Requires-Dist: spython>=0.2.0
Requires-Dist: packaging
Requires-Dist: Jinja2
Requires-Dist: jsonschema
Requires-Dist: ruamel.yaml
Requires-Dist: requests
Provides-Extra: all
Requires-Dist: spython>=0.2.0; extra == "all"
Requires-Dist: packaging; extra == "all"
Requires-Dist: Jinja2; extra == "all"
Requires-Dist: jsonschema; extra == "all"
Requires-Dist: ruamel.yaml; extra == "all"
Requires-Dist: requests; extra == "all"
Requires-Dist: pytest>=4.6.2; extra == "all"
Dynamic: author
Dynamic: author-email
Dynamic: classifier
Dynamic: description
Dynamic: description-content-type
Dynamic: home-page
Dynamic: keywords
Dynamic: license
Dynamic: maintainer
Dynamic: provides-extra
Dynamic: requires-dist
Dynamic: summary
